chora_gateway/__init__.py
chora_gateway/bootstrap/__init__.py
chora_gateway/bootstrap/startup.py
chora_gateway/core/__init__.py
chora_gateway/core/exceptions.py
chora_gateway/core/gateway.py
chora_gateway/core/models.py
chora_gateway/interfaces/__init__.py
chora_gateway/interfaces/api/__init__.py
chora_gateway/interfaces/cli/__init__.py
chora_gateway/interfaces/cli/main.py
chora_gateway/interfaces/http/__init__.py
chora_gateway/interfaces/http/server.py
chora_gateway/interfaces/mcp/__init__.py
chora_gateway/interfaces/mcp/server.py
chora_gateway/models/__init__.py
chora_gateway/registry/__init__.py
chora_gateway/registry/client.py
chora_gateway/registry/heartbeat.py
chora_gateway/utils/__init__.py
chora_gateway-0.1.0.dist-info/entry_points.txt
chora_gateway-0.1.0.dist-info/licenses/LICENSE
chora_gateway-0.1.0.dist-info/METADATA
chora_gateway-0.1.0.dist-info/WHEEL
chora_gateway-0.1.0.dist-info/RECORD
