Metadata-Version: 2.4
Name: chora-gateway
Version: 0.1.0
Summary: MCP Gateway for unified tool aggregation and request routing across multiple MCP servers
License: MIT
License-File: LICENSE
Keywords: mcp,gateway,routing,tool-aggregation,service-discovery
Author: Liminal Commons
Author-email: team@liminalcommons.org
Requires-Python: >=3.10,<4.0
Classifier: License :: OSI Approved :: MIT License
Classifier: Programming Language :: Python :: 3
Classifier: Programming Language :: Python :: 3.10
Classifier: Programming Language :: Python :: 3.11
Classifier: Programming Language :: Python :: 3.12
Classifier: Programming Language :: Python :: 3.13
Classifier: Programming Language :: Python :: 3.14
Requires-Dist: click (>=8.1.0,<9.0.0)
Requires-Dist: fastapi (>=0.109.0,<0.110.0)
Requires-Dist: httpx (>=0.27.0,<0.28.0)
Requires-Dist: pydantic (>=2.5.0,<3.0.0)
Requires-Dist: pyyaml (>=6.0,<7.0)
Requires-Dist: rich (>=13.0.0,<14.0.0)
Requires-Dist: uvicorn (>=0.27.0,<0.28.0)
Requires-Dist: websockets (>=12.0,<13.0)
Project-URL: Bug Tracker, https://github.com/liminalcommons/chora-gateway/issues
Project-URL: Homepage, https://github.com/liminalcommons/chora-gateway
Project-URL: Repository, https://github.com/liminalcommons/chora-gateway
